{"type":"FeatureCollection","features":[{"type":"Feature","properties":{"n":"初島漁港","k":"漁港"},"geometry":{"type":"Point","coordinates":[139.16545,35.04107]}},{"type":"Feature","properties":{"n":"網代漁港","k":"漁港"},"geometry":{"type":"Point","coordinates":[139.10238,35.04414]}},{"type":"Feature","properties":{"n":"富戸漁港","k":"漁港"},"geometry":{"type":"Point","coordinates":[139.13268,34.89581]}},{"type":"Feature","properties":{"n":"八幡野漁港","k":"漁港"},"geometry":{"type":"Point","coordinates":[139.10269,34.86915]}},{"type":"Feature","properties":{"n":"赤沢漁港","k":"漁港"},"geometry":{"type":"Point","coordinates":[139.08963,34.85776]}},{"type":"Feature","properties":{"n":"宇佐美漁港","k":"漁港"},"geometry":{"type":"Point","coordinates":[139.09129,35.00802]}},{"type":"Feature","properties":{"n":"大川漁港","k":"漁港"},"geometry":{"type":"Point","coordinates":[139.07713,34.84081]}},{"type":"Feature","properties":{"n":"北川漁港","k":"漁港"},"geometry":{"type":"Point","coordinates":[139.07714,34.82915]}},{"type":"Feature","properties":{"n":"波崎漁港","k":"漁港"},"geometry":{"type":"Point","coordinates":[140.84295,35.75291]}},{"type":"Feature","properties":{"n":"外川漁港","k":"漁港"},"geometry":{"type":"Point","coordinates":[140.8514,35.69632]}},{"type":"Feature","properties":{"n":"銚子漁港","k":"漁港"},"geometry":{"type":"Point","coordinates":[140.86362,35.74298]}},{"type":"Feature","properties":{"n":"市川漁港","k":"漁港"},"geometry":{"type":"Point","coordinates":[139.93481,35.66686]}},{"type":"Feature","properties":{"n":"伊戸漁港","k":"漁港"},"geometry":{"type":"Point","coordinates":[139.77179,34.95499]}},{"type":"Feature","properties":{"n":"川名漁港","k":"漁港"},"geometry":{"type":"Point","coordinates":[139.75737,34.96124]}},{"type":"Feature","properties":{"n":"洲崎漁港","k":"漁港"},"geometry":{"type":"Point","coordinates":[139.75485,34.96943]}},{"type":"Feature","properties":{"n":"栄の浦漁港","k":"漁港"},"geometry":{"type":"Point","coordinates":[139.76068,34.97582]}},{"type":"Feature","properties":{"n":"坂田漁港","k":"漁港"},"geometry":{"type":"Point","coordinates":[139.77457,34.97637]}},{"type":"Feature","properties":{"n":"波左間漁港","k":"漁港"},"geometry":{"type":"Point","coordinates":[139.7829,34.97415]}},{"type":"Feature","properties":{"n":"見物漁港","k":"漁港"},"geometry":{"type":"Point","coordinates":[139.79318,34.97415]}},{"type":"Feature","properties":{"n":"下原漁港","k":"漁港"},"geometry":{"type":"Point","coordinates":[139.8111,34.97856]}},{"type":"Feature","properties":{"n":"富崎漁港","k":"漁港"},"geometry":{"type":"Point","coordinates":[139.82348,34.92182]}},{"type":"Feature","properties":{"n":"船形漁港","k":"漁港"},"geometry":{"type":"Point","coordinates":[139.84679,35.0247]}},{"type":"Feature","properties":{"n":"金田漁港","k":"漁港"},"geometry":{"type":"Point","coordinates":[139.90288,35.42883]}},{"type":"Feature","properties":{"n":"牛込漁港","k":"漁港"},"geometry":{"type":"Point","coordinates":[139.93954,35.44327]}},{"type":"Feature","properties":{"n":"串浜漁港","k":"漁港"},"geometry":{"type":"Point","coordinates":[140.29674,35.14942]}},{"type":"Feature","properties":{"n":"鵜原漁港","k":"漁港"},"geometry":{"type":"Point","coordinates":[140.28421,35.13364]}},{"type":"Feature","properties":{"n":"守谷漁港","k":"漁港"},"geometry":{"type":"Point","coordinates":[140.25675,35.13665]}},{"type":"Feature","properties":{"n":"浜行川漁港","k":"漁港"},"geometry":{"type":"Point","coordinates":[140.23518,35.12156]}},{"type":"Feature","properties":{"n":"大沢漁港","k":"漁港"},"geometry":{"type":"Point","coordinates":[140.22036,35.11637]}},{"type":"Feature","properties":{"n":"勝浦東部漁港","k":"漁港"},"geometry":{"type":"Point","coordinates":[140.33063,35.15526]}},{"type":"Feature","properties":{"n":"松部漁港","k":"漁港"},"geometry":{"type":"Point","coordinates":[140.29126,35.14181]}},{"type":"Feature","properties":{"n":"勝浦漁港","k":"漁港"},"geometry":{"type":"Point","coordinates":[140.31224,35.14554]}},{"type":"Feature","properties":{"n":"天面漁港","k":"漁港"},"geometry":{"type":"Point","coordinates":[140.08343,35.06915]}},{"type":"Feature","properties":{"n":"太夫崎漁港","k":"漁港"},"geometry":{"type":"Point","coordinates":[140.07915,35.06272]}},{"type":"Feature","properties":{"n":"浜波太漁港","k":"漁港"},"geometry":{"type":"Point","coordinates":[140.10176,35.0772]}},{"type":"Feature","properties":{"n":"江見漁港","k":"漁港"},"geometry":{"type":"Point","coordinates":[140.06208,35.05877]}},{"type":"Feature","properties":{"n":"鴨川漁港","k":"漁港"},"geometry":{"type":"Point","coordinates":[140.1062,35.09498]}},{"type":"Feature","properties":{"n":"小糸川漁港","k":"漁港"},"geometry":{"type":"Point","coordinates":[139.85566,35.34772]}},{"type":"Feature","properties":{"n":"金谷漁港","k":"漁港"},"geometry":{"type":"Point","coordinates":[139.82067,35.16358]}},{"type":"Feature","properties":{"n":"萩生漁港","k":"漁港"},"geometry":{"type":"Point","coordinates":[139.82734,35.19885]}},{"type":"Feature","properties":{"n":"竹岡漁港","k":"漁港"},"geometry":{"type":"Point","coordinates":[139.83985,35.20946]}},{"type":"Feature","properties":{"n":"佐貫漁港","k":"漁港"},"geometry":{"type":"Point","coordinates":[139.86547,35.251]}},{"type":"Feature","properties":{"n":"大貫漁港","k":"漁港"},"geometry":{"type":"Point","coordinates":[139.85094,35.27745]}},{"type":"Feature","properties":{"n":"富津漁港","k":"漁港"},"geometry":{"type":"Point","coordinates":[139.81165,35.31961]}},{"type":"Feature","properties":{"n":"浦安漁港","k":"漁港"},"geometry":{"type":"Point","coordinates":[139.90203,35.65186]}},{"type":"Feature","properties":{"n":"飯岡漁港","k":"漁港"},"geometry":{"type":"Point","coordinates":[140.73224,35.69188]}},{"type":"Feature","properties":{"n":"片貝漁港","k":"漁港"},"geometry":{"type":"Point","coordinates":[140.46534,35.53546]}},{"type":"Feature","properties":{"n":"栗山川漁港","k":"漁港"},"geometry":{"type":"Point","coordinates":[140.58195,35.64196]}},{"type":"Feature","properties":{"n":"御宿漁港","k":"漁港"},"geometry":{"type":"Point","coordinates":[140.34868,35.1778]}},{"type":"Feature","properties":{"n":"岩和田漁港","k":"漁港"},"geometry":{"type":"Point","coordinates":[140.36618,35.1797]}},{"type":"Feature","properties":{"n":"岩船漁港","k":"漁港"},"geometry":{"type":"Point","coordinates":[140.39256,35.20859]}},{"type":"Feature","properties":{"n":"大原漁港","k":"漁港"},"geometry":{"type":"Point","coordinates":[140.4034,35.25442]}},{"type":"Feature","properties":{"n":"太東漁港","k":"漁港"},"geometry":{"type":"Point","coordinates":[140.40228,35.32885]}},{"type":"Feature","properties":{"n":"多田良漁港","k":"漁港"},"geometry":{"type":"Point","coordinates":[139.82845,35.03276]}},{"type":"Feature","properties":{"n":"富浦漁港","k":"漁港"},"geometry":{"type":"Point","coordinates":[139.82207,35.03887]}},{"type":"Feature","properties":{"n":"南無谷漁港","k":"漁港"},"geometry":{"type":"Point","coordinates":[139.82108,35.06746]}},{"type":"Feature","properties":{"n":"小浦漁港","k":"漁港"},"geometry":{"type":"Point","coordinates":[139.83674,35.07906]}},{"type":"Feature","properties":{"n":"高崎漁港","k":"漁港"},"geometry":{"type":"Point","coordinates":[139.84028,35.08407]}},{"type":"Feature","properties":{"n":"岩井袋漁港","k":"漁港"},"geometry":{"type":"Point","coordinates":[139.82873,35.10164]}},{"type":"Feature","properties":{"n":"勝山漁港","k":"漁港"},"geometry":{"type":"Point","coordinates":[139.82678,35.11053]}},{"type":"Feature","properties":{"n":"保田漁港","k":"漁港"},"geometry":{"type":"Point","coordinates":[139.83761,35.12997]}},{"type":"Feature","properties":{"n":"名倉漁港","k":"漁港"},"geometry":{"type":"Point","coordinates":[139.90817,34.90639]}},{"type":"Feature","properties":{"n":"野島漁港","k":"漁港"},"geometry":{"type":"Point","coordinates":[139.89373,34.90555]}},{"type":"Feature","properties":{"n":"川下漁港","k":"漁港"},"geometry":{"type":"Point","coordinates":[139.87096,34.90361]}},{"type":"Feature","properties":{"n":"白浜西部漁港","k":"漁港"},"geometry":{"type":"Point","coordinates":[139.84179,34.90361]}},{"type":"Feature","properties":{"n":"乙浜漁港","k":"漁港"},"geometry":{"type":"Point","coordinates":[139.92567,34.91083]}},{"type":"Feature","properties":{"n":"白子漁港","k":"漁港"},"geometry":{"type":"Point","coordinates":[139.97094,34.98527]}},{"type":"Feature","properties":{"n":"忽戸漁港","k":"漁港"},"geometry":{"type":"Point","coordinates":[139.964,34.9461]}},{"type":"Feature","properties":{"n":"川口漁港","k":"漁港"},"geometry":{"type":"Point","coordinates":[139.96039,34.93833]}},{"type":"Feature","properties":{"n":"平磯漁港","k":"漁港"},"geometry":{"type":"Point","coordinates":[139.95761,34.93611]}},{"type":"Feature","properties":{"n":"白間津漁港","k":"漁港"},"geometry":{"type":"Point","coordinates":[139.9415,34.92416]}},{"type":"Feature","properties":{"n":"大川漁港","k":"漁港"},"geometry":{"type":"Point","coordinates":[139.94817,34.92805]}},{"type":"Feature","properties":{"n":"七浦漁港","k":"漁港"},"geometry":{"type":"Point","coordinates":[139.954,34.93194]}},{"type":"Feature","properties":{"n":"千倉漁港","k":"漁港"},"geometry":{"type":"Point","coordinates":[139.964,34.95694]}},{"type":"Feature","properties":{"n":"和田漁港","k":"漁港"},"geometry":{"type":"Point","coordinates":[140.01371,35.0361]}},{"type":"Feature","properties":{"n":"浜荻漁港","k":"漁港"},"geometry":{"type":"Point","coordinates":[140.14242,35.11879]}},{"type":"Feature","properties":{"n":"小湊漁港","k":"漁港"},"geometry":{"type":"Point","coordinates":[140.1962,35.12026]}},{"type":"Feature","properties":{"n":"天津漁港","k":"漁港"},"geometry":{"type":"Point","coordinates":[140.15981,35.12248]}},{"type":"Feature","properties":{"n":"柴漁港","k":"漁港"},"geometry":{"type":"Point","coordinates":[139.63985,35.34355]}},{"type":"Feature","properties":{"n":"金沢漁港","k":"漁港"},"geometry":{"type":"Point","coordinates":[139.63623,35.33355]}},{"type":"Feature","properties":{"n":"秋谷漁港","k":"漁港"},"geometry":{"type":"Point","coordinates":[139.5993,35.23523]}},{"type":"Feature","properties":{"n":"久留和漁港","k":"漁港"},"geometry":{"type":"Point","coordinates":[139.59152,35.24578]}},{"type":"Feature","properties":{"n":"長井漁港","k":"漁港"},"geometry":{"type":"Point","coordinates":[139.60958,35.20718]}},{"type":"Feature","properties":{"n":"佐島漁港","k":"漁港"},"geometry":{"type":"Point","coordinates":[139.60596,35.22301]}},{"type":"Feature","properties":{"n":"平塚漁港","k":"漁港"},"geometry":{"type":"Point","coordinates":[139.36515,35.31383]}},{"type":"Feature","properties":{"n":"腰越漁港","k":"漁港"},"geometry":{"type":"Point","coordinates":[139.49208,35.30689]}},{"type":"Feature","properties":{"n":"片瀬漁港","k":"漁港"},"geometry":{"type":"Point","coordinates":[139.4785,35.30276]}},{"type":"Feature","properties":{"n":"二宮漁港","k":"漁港"},"geometry":{"type":"Point","coordinates":[139.24849,35.29188]}},{"type":"Feature","properties":{"n":"石橋漁港","k":"漁港"},"geometry":{"type":"Point","coordinates":[139.14222,35.22584]}},{"type":"Feature","properties":{"n":"米神漁港","k":"漁港"},"geometry":{"type":"Point","coordinates":[139.14211,35.2155]}},{"type":"Feature","properties":{"n":"江之浦漁港","k":"漁港"},"geometry":{"type":"Point","coordinates":[139.13823,35.19189]}},{"type":"Feature","properties":{"n":"小田原漁港","k":"漁港"},"geometry":{"type":"Point","coordinates":[139.14739,35.23966]}},{"type":"Feature","properties":{"n":"茅ヶ崎漁港","k":"漁港"},"geometry":{"type":"Point","coordinates":[139.39765,35.31549]}},{"type":"Feature","properties":{"n":"小坪漁港","k":"漁港"},"geometry":{"type":"Point","coordinates":[139.55652,35.2955]}},{"type":"Feature","properties":{"n":"北下浦漁港","k":"漁港"},"geometry":{"type":"Point","coordinates":[139.67509,35.19912]}},{"type":"Feature","properties":{"n":"金田漁港","k":"漁港"},"geometry":{"type":"Point","coordinates":[139.66513,35.15941]}},{"type":"Feature","properties":{"n":"毘沙門漁港","k":"漁港"},"geometry":{"type":"Point","coordinates":[139.65069,35.14052]}},{"type":"Feature","properties":{"n":"初声漁港","k":"漁港"},"geometry":{"type":"Point","coordinates":[139.61847,35.17218]}},{"type":"Feature","properties":{"n":"間口漁港","k":"漁港"},"geometry":{"type":"Point","coordinates":[139.67707,35.14469]}},{"type":"Feature","properties":{"n":"三崎漁港","k":"漁港"},"geometry":{"type":"Point","coordinates":[139.6193,35.13857]}},{"type":"Feature","properties":{"n":"真名瀬漁港","k":"漁港"},"geometry":{"type":"Point","coordinates":[139.56902,35.26911]}},{"type":"Feature","properties":{"n":"岩漁港","k":"漁港"},"geometry":{"type":"Point","coordinates":[139.14219,35.16234]}},{"type":"Feature","properties":{"n":"吉浜漁港","k":"漁港"},"geometry":{"type":"Point","coordinates":[139.12572,35.14941]}},{"type":"Feature","properties":{"n":"福浦漁港","k":"漁港"},"geometry":{"type":"Point","coordinates":[139.13184,35.15023]}},{"type":"Feature","properties":{"n":"伊東港","k":"港湾"},"geometry":{"type":"Point","coordinates":[139.12778,34.97303]}},{"type":"Feature","properties":{"n":"熱海港","k":"港湾"},"geometry":{"type":"Point","coordinates":[139.0824,35.08167]}},{"type":"Feature","properties":{"n":"千葉港","k":"港湾"},"geometry":{"type":"Point","coordinates":[140.00355,35.57307]}},{"type":"Feature","properties":{"n":"木更津港","k":"港湾"},"geometry":{"type":"Point","coordinates":[139.82814,35.38509]}},{"type":"Feature","properties":{"n":"館山港","k":"港湾"},"geometry":{"type":"Point","coordinates":[139.84157,34.99771]}},{"type":"Feature","properties":{"n":"興津港","k":"港湾"},"geometry":{"type":"Point","coordinates":[140.25276,35.1294]}},{"type":"Feature","properties":{"n":"名洗港","k":"港湾"},"geometry":{"type":"Point","coordinates":[140.83317,35.70236]}},{"type":"Feature","properties":{"n":"上総湊港","k":"港湾"},"geometry":{"type":"Point","coordinates":[139.86137,35.22297]}},{"type":"Feature","properties":{"n":"浜金谷港","k":"港湾"},"geometry":{"type":"Point","coordinates":[139.81208,35.17198]}},{"type":"Feature","properties":{"n":"東京港","k":"港湾"},"geometry":{"type":"Point","coordinates":[139.80492,35.57386]}},{"type":"Feature","properties":{"n":"横浜港","k":"港湾"},"geometry":{"type":"Point","coordinates":[139.69346,35.41591]}},{"type":"Feature","properties":{"n":"川崎港","k":"港湾"},"geometry":{"type":"Point","coordinates":[139.77427,35.4871]}},{"type":"Feature","properties":{"n":"横須賀港","k":"港湾"},"geometry":{"type":"Point","coordinates":[139.70444,35.28643]}},{"type":"Feature","properties":{"n":"大磯港","k":"港湾"},"geometry":{"type":"Point","coordinates":[139.32041,35.30528]}},{"type":"Feature","properties":{"n":"真鶴港","k":"港湾"},"geometry":{"type":"Point","coordinates":[139.15006,35.14948]}},{"type":"Feature","properties":{"n":"湘南港","k":"港湾"},"geometry":{"type":"Point","coordinates":[139.48754,35.3001]}},{"type":"Feature","properties":{"n":"葉山港","k":"港湾"},"geometry":{"type":"Point","coordinates":[139.56588,35.28276]}}]}